<?xml version="1.0" encoding="UTF-8"?>
<databaseChangeLog
  xmlns:xsi="http://www.w3.org/2001/XMLSchema-instance"
  xmlns="http://www.liquibase.org/xml/ns/dbchangelog"
  xsi:schemaLocation="http://www.liquibase.org/xml/ns/dbchangelog
    http://www.liquibase.org/xml/ns/dbchangelog/dbchangelog-4.0.xsd">

  <changeSet id="20260601-1" author="antigravity">
    <createTable tableName="inventories">
      <column name="id" type="UUID" defaultValueComputed="gen_random_uuid()">
        <constraints primaryKey="true" nullable="false"/>
      </column>
      <column name="product_id" type="UUID">
        <constraints nullable="false" unique="true"/>
      </column>
      <column name="available_quantity" type="INT" defaultValueNumeric="0">
        <constraints nullable="false"/>
      </column>
      <column name="reserved_quantity" type="INT" defaultValueNumeric="0">
        <constraints nullable="false"/>
      </column>
      <column name="version" type="BIGINT" defaultValueNumeric="0">
        <constraints nullable="false"/>
      </column>
      <column name="created_at" type="TIMESTAMP" defaultValueComputed="CURRENT_TIMESTAMP">
        <constraints nullable="false"/>
      </column>
      <column name="updated_at" type="TIMESTAMP" defaultValueComputed="CURRENT_TIMESTAMP">
        <constraints nullable="false"/>
      </column>
    </createTable>

    <createTable tableName="inventory_reservations">
      <column name="id" type="UUID" defaultValueComputed="gen_random_uuid()">
        <constraints primaryKey="true" nullable="false"/>
      </column>
      <column name="inventory_id" type="UUID">
        <constraints nullable="false"/>
      </column>
      <column name="order_id" type="UUID">
        <constraints nullable="false"/>
      </column>
      <column name="reserved_quantity" type="INT">
        <constraints nullable="false"/>
      </column>
      <column name="status" type="VARCHAR(20)">
        <constraints nullable="false"/>
      </column>
      <column name="created_at" type="TIMESTAMP" defaultValueComputed="CURRENT_TIMESTAMP">
        <constraints nullable="false"/>
      </column>
      <column name="updated_at" type="TIMESTAMP" defaultValueComputed="CURRENT_TIMESTAMP">
        <constraints nullable="false"/>
      </column>
    </createTable>

    <addUniqueConstraint tableName="inventory_reservations"
                         columnNames="inventory_id, order_id"
                         constraintName="uq_inventory_order"/>

    <addForeignKeyConstraint baseTableName="inventory_reservations" baseColumnNames="inventory_id"
                             constraintName="fk_reservations_inventory"
                             referencedTableName="inventories" referencedColumnNames="id"
                             onDelete="RESTRICT"/>
  </changeSet>
</databaseChangeLog>
